pygifconverter_mj/__init__.py
pygifconverter_mj/gifconverter.py
pygifconvter_mj-1.0.3.dist-info/LICENSE
pygifconvter_mj-1.0.3.dist-info/METADATA
pygifconvter_mj-1.0.3.dist-info/WHEEL
pygifconvter_mj-1.0.3.dist-info/top_level.txt
pygifconvter_mj-1.0.3.dist-info/RECORD
