Metadata-Version: 2.2
Name: pygifconvter_mj
Version: 1.0.3
Summary: Test package for distribution
Home-page: 
Download-URL: 
Author: Eunki7
Author-email: outsider7224@gmail.com
Keywords: GIFCONVERTER,gifconverter
Classifier: Programming Language :: Python :: 3
Classifier: License :: OSI Approved :: MIT License
Classifier: Operating System :: OS Independent
Requires-Python: >=3
License-File: LICENSE
Requires-Dist: pillow
Dynamic: author
Dynamic: author-email
Dynamic: classifier
Dynamic: keywords
Dynamic: requires-dist
Dynamic: requires-python
Dynamic: summary
